Metadata-Version: 1.1
Name: audiotrans-transform-istft
Version: 0.1.0.dev2
Summary: audiotrans transform module to Inverse Short-Time Fourier Transformation (ISTFT)
Home-page: https://github.com/keik/audiotrans-transform-istft
Author: keik
Author-email: k4t0.kei@gmail.com
License: MIT
Platform: UNKNOWN
Classifier: License :: OSI Approved :: MIT License
Classifier: Intended Audience :: Developers
Classifier: Topic :: Multimedia :: Sound/Audio :: Conversion
Classifier: Programming Language :: Python
Classifier: Programming Language :: Python :: 3
Classifier: Programming Language :: Python :: 3.5
